azc/__init__.py
azc/mod/__init__.py
azc/mod/func.py
azc1-0.0.1.dist-info/METADATA
azc1-0.0.1.dist-info/WHEEL
azc1-0.0.1.dist-info/top_level.txt
azc1-0.0.1.dist-info/RECORD
