Metadata-Version: 2.1
Name: azc1
Version: 0.0.1
Summary: 你好
Home-page: UNKNOWN
Author: a1
Author-email: xxx@123.com
License: UNKNOWN
Platform: UNKNOWN
Requires-Python: >=3.6
